django_migrations_ruff_formatter/__init__.py
django_migrations_ruff_formatter/apps.py
django_migrations_ruff_formatter/patch_formatters.py
django_migrations_ruff_formatter-0.1.3.dist-info/METADATA
django_migrations_ruff_formatter-0.1.3.dist-info/WHEEL
django_migrations_ruff_formatter-0.1.3.dist-info/top_level.txt
django_migrations_ruff_formatter-0.1.3.dist-info/RECORD
